huaweicloudsdkcodeartscheck/__init__.py
huaweicloudsdkcodeartscheck/v2/__init__.py
huaweicloudsdkcodeartscheck/v2/codeartscheck_async_client.py
huaweicloudsdkcodeartscheck/v2/codeartscheck_client.py
huaweicloudsdkcodeartscheck/v2/model/__init__.py
huaweicloudsdkcodeartscheck/v2/model/check_config_info.py
huaweicloudsdkcodeartscheck/v2/model/check_parameters_request.py
huaweicloudsdkcodeartscheck/v2/model/check_parameters_response.py
huaweicloudsdkcodeartscheck/v2/model/check_record_data_info.py
huaweicloudsdkcodeartscheck/v2/model/check_record_issue_counts_info.py
huaweicloudsdkcodeartscheck/v2/model/check_record_request.py
huaweicloudsdkcodeartscheck/v2/model/check_record_response.py
huaweicloudsdkcodeartscheck/v2/model/check_ruleset_parameters_request.py
huaweicloudsdkcodeartscheck/v2/model/check_ruleset_parameters_response.py
huaweicloudsdkcodeartscheck/v2/model/config_task_parameter_body.py
huaweicloudsdkcodeartscheck/v2/model/create_ruleset_request.py
huaweicloudsdkcodeartscheck/v2/model/create_ruleset_response.py
huaweicloudsdkcodeartscheck/v2/model/create_task_request.py
huaweicloudsdkcodeartscheck/v2/model/create_task_request_v2.py
huaweicloudsdkcodeartscheck/v2/model/create_task_response.py
huaweicloudsdkcodeartscheck/v2/model/custom_attributes.py
huaweicloudsdkcodeartscheck/v2/model/custom_attributes_rule.py
huaweicloudsdkcodeartscheck/v2/model/defect_events.py
huaweicloudsdkcodeartscheck/v2/model/defect_fragment_v2.py
huaweicloudsdkcodeartscheck/v2/model/defect_info_v2.py
huaweicloudsdkcodeartscheck/v2/model/delete_ruleset_request.py
huaweicloudsdkcodeartscheck/v2/model/delete_ruleset_response.py
huaweicloudsdkcodeartscheck/v2/model/delete_task_request.py
huaweicloudsdkcodeartscheck/v2/model/delete_task_response.py
huaweicloudsdkcodeartscheck/v2/model/ignore_path_setting_item.py
huaweicloudsdkcodeartscheck/v2/model/inc_config_v2.py
huaweicloudsdkcodeartscheck/v2/model/list_rules_request.py
huaweicloudsdkcodeartscheck/v2/model/list_rules_response.py
huaweicloudsdkcodeartscheck-3.1.184.dist-info/METADATA
huaweicloudsdkcodeartscheck-3.1.184.dist-info/WHEEL
huaweicloudsdkcodeartscheck-3.1.184.dist-info/licenses/LICENSE
huaweicloudsdkcodeartscheck-3.1.184.dist-info/RECORD
